yandex_geocoder/__init__.py
yandex_geocoder/client.py
yandex_geocoder/exceptions.py
yandex_geocoder-3.0.0.dist-info/WHEEL
yandex_geocoder-3.0.0.dist-info/LICENSE
yandex_geocoder-3.0.0.dist-info/METADATA
yandex_geocoder-3.0.0.dist-info/RECORD
