Metadata-Version: 2.1
Name: yandex-geocoder
Version: 3.0.0
Summary: Simple library for getting address or coordinates via Yandex geocoder
Home-page: https://github.com/sivakov512/yandex-geocoder
License: MIT
Author: Nikita Sivakov
Author-email: sivakov512@icloud.com
Requires-Python: >=3.9,<4.0
Classifier: License :: OSI Approved :: MIT License
Classifier: Programming Language :: Python :: 3
Classifier: Programming Language :: Python :: 3.9
Classifier: Programming Language :: Python :: 3.10
Classifier: Programming Language :: Python :: 3.11
Requires-Dist: requests (>=2.28.1,<3.0.0)
Project-URL: Repository, https://github.com/sivakov512/yandex-geocoder
